LICENSE
plafosim/__init__.py
plafosim/algorithms/__init__.py
plafosim/algorithms/dummy.py
plafosim/algorithms/speed_position.py
plafosim/cli/__init__.py
plafosim/cli/img2video.py
plafosim/cli/plafosim.py
plafosim/cli/trace_replay.py
plafosim/emissions.py
plafosim/formation_algorithm.py
plafosim/gui.py
plafosim/infrastructure.py
plafosim/mobility.py
plafosim/platoon.py
plafosim/platoon_role.py
plafosim/platooning_vehicle.py
plafosim/simulator.py
plafosim/spawning.py
plafosim/statistics.py
plafosim/sumocfg/freeway.gui.xml
plafosim/sumocfg/freeway.net.xml
plafosim/sumocfg/freeway.rou.xml
plafosim/sumocfg/freeway.sumo.cfg
plafosim/util.py
plafosim/vehicle.py
plafosim/vehicle_type.py
plafosim-0.17.4.dist-info/LICENSE
plafosim-0.17.4.dist-info/METADATA
plafosim-0.17.4.dist-info/WHEEL
plafosim-0.17.4.dist-info/entry_points.txt
plafosim-0.17.4.dist-info/RECORD
