Metadata-Version: 2.1
Name: plafosim
Version: 0.17.4
Summary: A simple and scalable simulator for platoon formation.
Home-page: https://www.plafosim.de
License: GPL-3.0-or-later
Keywords: Algorithm,Engineering,Experiment,Platoon,Platoon Formation,Platooning,Platoon Maneuver,Research,Science,Simulation,Simulator
Author: Julian Heinovski
Author-email: heinovski@ccs-labs.org
Maintainer: Julian Heinovski
Maintainer-email: heinovski@ccs-labs.org
Requires-Python: >=3.8,<3.10
Classifier: Development Status :: 4 - Beta
Classifier: Intended Audience :: Developers
Classifier: Intended Audience :: Science/Research
Classifier: License :: OSI Approved :: GNU General Public License v3 or later (GPLv3+)
Classifier: Programming Language :: Python :: 3
Classifier: Programming Language :: Python :: 3.8
Classifier: Programming Language :: Python :: 3.9
Classifier: Topic :: Scientific/Engineering
Provides-Extra: solver
Requires-Dist: numpy (>=1.19,<2.0)
Requires-Dist: ortools (>=9.0,<10.0) ; extra == "solver"
Requires-Dist: pandas (>=1.1,<2.0)
Requires-Dist: tqdm (>=4.61,<5.0)
Project-URL: Changelog, https://github.com/heinovski/plafosim/blob/master/CHANGELOG.md
Project-URL: Documentation, https://plafosim.readthedocs.io/
Project-URL: Repository, https://github.com/heinovski/plafosim
